[{"file":"provider_cache_production_id","country":"Indonesia","category":"Most popular","provider_list":[74,77,72,7],"key_name":"most_popular_id","name":"provider"},{"file":"provider_cache_production_my","country":"Malaysia","category":"Banks in Malaysia","provider_list":[66,81,65,75,68,69,67,86,87,88],"key_name":"bank_my","name":"provider"},{"file":"provider_cache_production_my","country":"Malaysia","category":"Services","provider_list":[7,80,79],"key_name":"service_malaysia","name":"provider"},{"file":"provider_cache_production_in","country":"India","category":"Bank in India","provider_list":[163,98,104,99,102,101,94,95,96,97,103,100,7],"key_name":"bank_in","name":"provider"},{"file":"provider_cache_production_us","country":"United States","category":"Bank in US","provider_list":[55,60,63,64],"key_name":"bank_us","name":"provider"},{"country":"United States","category":"Online Service","key_name":"online_service","name":"provider","file":"provider_cache_production_us","provider_list":[79,80,7]},{"file":"provider_cache_production_hk","country":"Hong Kong","category":"Bank","provider_list":[111,106,110,108,107,112,109,113,114,115,116,117,118,119,120,124,125,126],"key_name":"bank_hongkong","name":"provider"},{"file":"provider_cache_production_th","country":"Thailand","category":"Thai Bank","provider_list":[82,41,85,105,47,42,49,7],"key_name":"bank_thailand","name":"provider"},{"file":"provider_cache_production_hk","country":"Hong Kong","category":"New","provider_list":[120,111,124,125,126],"key_name":"bank_hongkong_new","name":"provider"},{"file":"provider_cache_production_au","country":"Australia","category":"Bank","provider_list":[129,130,133,127,128,131,132],"key_name":"bank_au","name":"provider"},{"file":"provider_cache_production_jp","country":"Japan","category":"Banks","provider_list":[134,135,138,136,137,140,7],"key_name":"bank_japan","name":"provider"},{"file":"provider_cache_production_ru","country":"Russian Federation","category":"Banks","provider_list":[141,143,142,144,145,146,147,148,149],"key_name":"bank_ru","name":"provider"},{"file":"provider_cache_production_br","country":"Brazil","category":"Banks","provider_list":[150,151,152,153,154,155],"key_name":"bank_br","name":"provider"},{"file":"provider_cache_production_gb","country":"United Kingdom","category":"Banks","provider_list":[157,158,159,160,161,162,156,7],"key_name":"bank_gb","name":"provider"},{"file":"provider_cache_production_in","country":"India","category":"Service","provider_list":[7],"key_name":"service_in","name":"provider"},{"file":"provider_cache_production_au","country":"Australia","category":"Other","provider_list":[7],"key_name":"service_au","name":"provider"},{"file":"provider_cache_production_ru","country":"Russian Federation","category":"Other","provider_list":[7],"key_name":"service_ru","name":"provider"},{"file":"provider_cache_production_it","country":"Italy","category":"Service","provider_list":[7],"key_name":"service_it","name":"provider"},{"country":"Thailand","category":"Service","key_name":"service_thailand","name":"provider","file":"provider_cache_production_th","provider_list":[7,80]},{"file":"provider_cache_production_gb","country":"United Kingdom","category":"Service","provider_list":[7,79],"key_name":"service_gb","name":"provider"},{"country":"Viet Nam","category":"Ngân hàng ở Việt Nam","key_name":"most_popular_vn","name":"provider","file":"provider_cache_production_vn","provider_list":[8,14,24,28,15,5,17,18,19,25,27,30,20,33,36,50,90,91,92]},{"country":"Viet Nam","category":"Mới","key_name":"bank_vietnam_new","name":"provider","file":"provider_cache_production_vn","provider_list":[123,121,122,20,22,78,30,92]},{"file":"provider_cache_production_vn","country":"Viet Nam","category":"Dịch vụ","provider_list":[4,7,1],"key_name":"service_vietnam","name":"provider"},{"file":"provider_cache_production_hk","country":"Hong Kong","category":"Service","provider_list":[7],"key_name":"service_hongkong","name":"provider"},{"file":"provider_cache_production_id","country":"Indonesia","category":"Others","provider_list":[76,7],"key_name":"credit_card_id","name":"provider"},{"file":"provider_cache_production_it","country":"Italy","category":"Banks","provider_list":[169,170,172,173,174,175,176,177],"key_name":"bank_it","name":"provider"},{"file":"provider_cache_production_ph","country":"Philippines","category":"Banks","provider_list":[165,166,167,168],"key_name":"bank_ph","name":"provider"},{"file":"provider_cache_production_de","country":"Germany","category":"Banks","provider_list":[178],"key_name":"bank_de","name":"provider"},{"file":"provider_cache_production_id","country":"Indonesia","category":"Banks","provider_list":[179,180,181],"key_name":"bank_id","name":"provider"},{"file":"provider_cache_production_la","country":"Lao People's Democratic Republic","category":"Banks","provider_list":[184,185,186,187,188],"key_name":"bank_la","name":"provider"},{"file":"provider_cache_production_kh","country":"Cambodia","category":"Banks","provider_list":[189,190,191,192,193,194,195,196,197],"key_name":"bank_kh","name":"provider"},{"file":"provider_cache_production_tw","country":"Taiwan","category":"Banks","provider_list":[198,199,200,201,202,203,204],"key_name":"bank_tw","name":"provider"},{"file":"provider_cache_production_jp","country":"Japan","category":"Service","provider_list":[7],"key_name":"service_japan","name":"provider"}]